[{"OriginalCompleteBefore": "payloadValue = new DateTime(clock.millis())", "OriginalCompleteAfter": "payloadValue = clock.instant().atZone(ZoneId.systemDefault())", "Before": "new DateTime(clock.millis())", "After": "clock.instant().atZone(ZoneId.systemDefault())", "Project": "elasticsearch", "Commit": "9b64558efb71f1564cd97c02e427a52f521cef8c", "CompilationUnit": "org.elasticsearch.xpack.watcher.condition.CompareConditionTests", "LineNos": {"_1": 181, "_2": 182}, "Names": {"_1": "payloadValue", "_2": "payloadValue"}, "TemplateVariableToCodeBefore": {"v0": "clock"}, "RelevantImports": ["java.time.ZoneId", "org.joda.time.DateTime"], "TemplateVariableToCodeAfter": {"v0": "clock"}, "isRelevant": "AssignedTo", "isSafe": true}]