[{"OriginalCompleteBefore": "audiblyAlerted=ranking.audiblyAlerted();", "OriginalCompleteAfter": "lastAudiblyAlertedMs=ranking.getLastAudiblyAlertedMillis();", "Before": "audiblyAlerted=ranking.audiblyAlerted()", "After": "audiblyAlerted=ranking.getLastAudiblyAlertedMillis()", "Project": "platform_frameworks_base", "Commit": "7306b9055421a6cae934a858f0827f797eade261", "CompilationUnit": "com.android.systemui.statusbar.notification.NotificationData.Entry", "LineNos": {"_1": 106, "_2": 106}, "Names": {"_1": "audiblyAlerted", "_2": "lastAudiblyAlertedMs"}, "TemplateVariableToCodeBefore": {"TCIVar": "audiblyAlerted", "v1": "ranking"}, "RelevantImports": [], "TemplateVariableToCodeAfter": {"TCIVar": "audiblyAlerted", "v1": "ranking"}, "isRelevant": "Uses", "isSafe": false}]