[{"OriginalCompleteBefore": "result = coyoteRequest.getCharacterEncoding()", "OriginalCompleteAfter": "charset = coyoteRequest.getCharset()", "Before": "coyoteRequest.getCharacterEncoding()", "After": "coyoteRequest.getCharset()", "Project": "tomcat", "Commit": "b2bab804b543bfe181fe435efe35628ce0e21b39", "CompilationUnit": "org.apache.catalina.connector.Request", "LineNos": {"_1": 974, "_2": 974}, "Names": {"_1": "result", "_2": "charset"}, "TemplateVariableToCodeBefore": {"v0": "coyoteRequest"}, "RelevantImports": [], "TemplateVariableToCodeAfter": {"v0": "coyoteRequest"}, "isRelevant": "AssignedTo", "isSafe": true}, {"OriginalCompleteBefore": "String result=coyoteRequest.getCharacterEncoding();", "OriginalCompleteAfter": "Charset charset=coyoteRequest.getCharset();", "Before": "coyoteRequest.getCharacterEncoding()", "After": "coyoteRequest.getCharset()", "Project": "tomcat", "Commit": "b2bab804b543bfe181fe435efe35628ce0e21b39", "CompilationUnit": "org.apache.catalina.connector.Request", "LineNos": {"_1": 974, "_2": 974}, "Names": {"_1": "result", "_2": "charset"}, "TemplateVariableToCodeBefore": {"v0": "coyoteRequest"}, "RelevantImports": [], "TemplateVariableToCodeAfter": {"v0": "coyoteRequest"}, "isRelevant": "AssignedTo", "isSafe": true}]