[{"OriginalCompleteBefore": "partition=getPartitionForProcedure(catProc,task);", "OriginalCompleteAfter": "partitions=getPartitionsForProcedure(catProc,task);", "Before": "partition=getPartitionForProcedure(catProc,task)", "After": "partition=getPartitionsForProcedure(catProc,task)", "Project": "voltdb", "Commit": "e30b34be24a0c50eddccde281a77114e59e29b5b", "CompilationUnit": "org.voltdb.InvocationDispatcher", "LineNos": {"_1": 476, "_2": 476}, "Names": {"_1": "partition", "_2": "partitions"}, "TemplateVariableToCodeBefore": {"TCIVar": "partition"}, "RelevantImports": [], "TemplateVariableToCodeAfter": {"TCIVar": "partition"}, "isRelevant": "Uses", "isSafe": true}]