[{"OriginalCompleteBefore": "return String.format(STR0,this.getClass().getSimpleName(),hashCode(),_curr.get(),_max.get(),_total.get());", "OriginalCompleteAfter": "return String.format(STR0,this.getClass().getSimpleName(),hashCode(),_current.get(),_max.get(),_total.sum());", "Before": "String.format(STR0,this.getClass().getSimpleName(),hashCode(),_curr.get(),_max.get(),_total.get())", "After": "String.format(STR0,this.getClass().getSimpleName(),hashCode(),_current.get(),_max.get(),_total.sum())", "Project": "jetty.project", "Commit": "91bef559247e33abca341be3d273339d02530195", "CompilationUnit": "org.eclipse.jetty.util.statistic.CounterStatistic", "LineNos": {"_1": 38, "_2": 37}, "Names": {"_1": "_total", "_2": "_total"}, "TemplateVariableToCodeBefore": {"TCIVar": "_total", "v1": "_max.get()", "v2": "this.getClass().getSimpleName()", "v3": "hashCode()", "v4": "STR0"}, "RelevantImports": ["java.lang.String"], "TemplateVariableToCodeAfter": {"TCIVar": "_total", "v1": "_max.get()", "v2": "this.getClass().getSimpleName()", "v3": "hashCode()", "v4": "STR0"}, "isRelevant": "Uses", "isSafe": true}]