[{"OriginalCompleteBefore": "dest.writeString(mServiceName);", "OriginalCompleteAfter": "dest.writeByteArray(mServiceName);", "Before": "dest.writeString(mServiceName)", "After": "dest.writeByteArray(mServiceName)", "Project": "platform_frameworks_base", "Commit": "01db037f455b7326e7952bb10d1deccebcfdd66c", "CompilationUnit": "android.net.wifi.nan.SubscribeConfig", "LineNos": {"_1": 79, "_2": 80}, "Names": {"_1": "mServiceName", "_2": "mServiceName"}, "TemplateVariableToCodeBefore": {"TCIVar": "mServiceName", "v0": "dest"}, "RelevantImports": [], "TemplateVariableToCodeAfter": {"TCIVar": "mServiceName", "v0": "dest"}, "isRelevant": "Uses", "isSafe": true}, {"OriginalCompleteBefore": "dest.writeString(mServiceName);", "OriginalCompleteAfter": "dest.writeByteArray(mServiceName);", "Before": "dest.writeString(mServiceName)", "After": "dest.writeByteArray(mServiceName)", "Project": "platform_frameworks_base", "Commit": "01db037f455b7326e7952bb10d1deccebcfdd66c", "CompilationUnit": "android.net.wifi.nan.PublishConfig", "LineNos": {"_1": 61, "_2": 62}, "Names": {"_1": "mServiceName", "_2": "mServiceName"}, "TemplateVariableToCodeBefore": {"TCIVar": "mServiceName", "v0": "dest"}, "RelevantImports": [], "TemplateVariableToCodeAfter": {"TCIVar": "mServiceName", "v0": "dest"}, "isRelevant": "Uses", "isSafe": true}, {"OriginalCompleteBefore": "dest.writeString(mServiceName);", "OriginalCompleteAfter": "dest.writeByteArray(mServiceName);", "Before": "dest.writeString(mServiceName)", "After": "dest.writeByteArray(mServiceName)", "Project": "platform_frameworks_base", "Commit": "adfbfb3a939f5662cb62cdd6b5d7cce5494a159e", "CompilationUnit": "android.net.wifi.nan.SubscribeConfig", "LineNos": {"_1": 79, "_2": 80}, "Names": {"_1": "mServiceName", "_2": "mServiceName"}, "TemplateVariableToCodeBefore": {"TCIVar": "mServiceName", "v0": "dest"}, "RelevantImports": [], "TemplateVariableToCodeAfter": {"TCIVar": "mServiceName", "v0": "dest"}, "isRelevant": "Uses", "isSafe": true}, {"OriginalCompleteBefore": "dest.writeString(mServiceName);", "OriginalCompleteAfter": "dest.writeByteArray(mServiceName);", "Before": "dest.writeString(mServiceName)", "After": "dest.writeByteArray(mServiceName)", "Project": "platform_frameworks_base", "Commit": "adfbfb3a939f5662cb62cdd6b5d7cce5494a159e", "CompilationUnit": "android.net.wifi.nan.PublishConfig", "LineNos": {"_1": 61, "_2": 62}, "Names": {"_1": "mServiceName", "_2": "mServiceName"}, "TemplateVariableToCodeBefore": {"TCIVar": "mServiceName", "v0": "dest"}, "RelevantImports": [], "TemplateVariableToCodeAfter": {"TCIVar": "mServiceName", "v0": "dest"}, "isRelevant": "Uses", "isSafe": true}]