[{"OriginalCompleteBefore": "i = 0", "OriginalCompleteAfter": "i = iterations.incrementAndGet()", "Before": "0", "After": "iterations.incrementAndGet()", "Project": "redisson", "Commit": "8ffedea17342ae5062362033f85b8b55eb1b17a4", "CompilationUnit": "org.redisson.RedissonRemoteServiceTest.RemoteImpl", "LineNos": {"_1": 147, "_2": 148}, "Names": {"_1": "i", "_2": "i"}, "TemplateVariableToCodeBefore": {}, "RelevantImports": [], "TemplateVariableToCodeAfter": {"xyz": "iterations.incrementAndGet()"}, "isRelevant": "AssignedTo", "isSafe": false}]