[{"OriginalCompleteBefore": "newActiveAudioPlaybackClientUids = new ArrayList<>()", "OriginalCompleteAfter": "players = mAudioPlayersForUid.get(uid)", "Before": "new ArrayList<>()", "After": "mAudioPlayersForUid.get(uid)", "Project": "platform_frameworks_base", "Commit": "18341301443d0c8e1bd4fc1ba9a7c909593eb918", "CompilationUnit": "com.android.server.media.AudioPlaybackMonitor", "LineNos": {"_1": 110, "_2": 135}, "Names": {"_1": "newActiveAudioPlaybackClientUids", "_2": "players"}, "TemplateVariableToCodeBefore": {"xyz": "new ArrayList<>()"}, "RelevantImports": ["java.util.ArrayList"], "TemplateVariableToCodeAfter": {"xyz": "mAudioPlayersForUid.get(uid)"}, "isRelevant": "AssignedTo", "isSafe": false}, {"OriginalCompleteBefore": "newActiveAudioPlaybackClientUids = new ArrayList<>()", "OriginalCompleteAfter": "players = mAudioPlayersForUid.get(uid)", "Before": "new ArrayList<>()", "After": "mAudioPlayersForUid.get(uid)", "Project": "platform_frameworks_base", "Commit": "875e697f9c6624f34851e09b4bf1ccef810f59e9", "CompilationUnit": "com.android.server.media.AudioPlaybackMonitor", "LineNos": {"_1": 110, "_2": 135}, "Names": {"_1": "newActiveAudioPlaybackClientUids", "_2": "players"}, "TemplateVariableToCodeBefore": {"xyz": "new ArrayList<>()"}, "RelevantImports": ["java.util.ArrayList"], "TemplateVariableToCodeAfter": {"xyz": "mAudioPlayersForUid.get(uid)"}, "isRelevant": "AssignedTo", "isSafe": false}]