[{"OriginalCompleteBefore": "db=CamelContextHelper.mandatoryLookup(getCamelContext(),remaining,Mongo.class);", "OriginalCompleteAfter": "db=CamelContextHelper.mandatoryLookup(getCamelContext(),remaining,MongoClient.class);", "Before": "CamelContextHelper.mandatoryLookup(getCamelContext(),remaining,Mongo.class)", "After": "CamelContextHelper.mandatoryLookup(getCamelContext(),remaining,MongoClient.class)", "Project": "camel", "Commit": "700175344f057c8f1a24e7925261dcaf02c4fe5b", "CompilationUnit": "org.apache.camel.component.mongodb.MongoDbComponent", "LineNos": {"_1": 40, "_2": 42}, "Names": {"_1": "db", "_2": "db"}, "TemplateVariableToCodeBefore": {"v0": "getCamelContext()", "v1": "remaining"}, "RelevantImports": ["org.apache.camel.util.CamelContextHelper"], "TemplateVariableToCodeAfter": {"v0": "getCamelContext()", "v1": "remaining"}, "isRelevant": "AssignedTo", "isSafe": true}]