[{"OriginalCompleteBefore": "return conditions().displayed();", "OriginalCompleteAfter": "return input.displayed();", "Before": "conditions().displayed()", "After": "input.displayed()", "Project": "FluentLenium", "Commit": "1c6f6c21208b4449a859c730741c2b78332b65d2", "CompilationUnit": "org.fluentlenium.core.wait.FluentWaitElementEachMatcher.displayed.until", "LineNos": {"_1": 102, "_2": 90}, "Names": {"_1": "apply", "_2": "apply"}, "TemplateVariableToCodeBefore": {"xyz": "conditions().displayed()"}, "RelevantImports": [], "TemplateVariableToCodeAfter": {"xyz": "input.displayed()"}, "isRelevant": "Returns", "isSafe": false}]