[{"OriginalCompleteBefore": "return userSessionId != null && denied;", "OriginalCompleteAfter": "return denied;", "Before": "userSessionId != null && denied", "After": "denied", "Project": "keycloak", "Commit": "298ab0bc3eee93b35512211cba4d37edaf1905e3", "CompilationUnit": "org.keycloak.models.OAuth2DeviceCodeModel", "LineNos": {"_1": 49, "_2": 49}, "Names": {"_1": "denied", "_2": "denied"}, "TemplateVariableToCodeBefore": {"TCIVar": "denied"}, "RelevantImports": [], "TemplateVariableToCodeAfter": {"TCIVar": "denied"}, "isRelevant": "Uses", "isSafe": false}]