[{"OriginalCompleteBefore": "loadData.getBrokerData().get(broker).getPreallocatedBundleData().put(bundle,data);", "OriginalCompleteAfter": "loadData.getBrokerData().get(broker.get()).getPreallocatedBundleData().put(bundle,data);", "Before": "loadData.getBrokerData().get(broker).getPreallocatedBundleData()", "After": "loadData.getBrokerData().get(broker.get()).getPreallocatedBundleData()", "Project": "pulsar", "Commit": "d6d4fa3a1103f650bf16e74429f82db3d33fe739", "CompilationUnit": "org.apache.pulsar.broker.loadbalance.impl.ModularLoadManagerImpl", "LineNos": {"_1": 740, "_2": 739}, "Names": {"_1": "broker", "_2": "broker"}, "TemplateVariableToCodeBefore": {"TCIVar": "broker", "v1": "loadData"}, "RelevantImports": [], "TemplateVariableToCodeAfter": {"TCIVar": "broker", "v1": "loadData"}, "isRelevant": "Uses", "isSafe": true}]