[{"OriginalCompleteBefore": "FluidRenderer.renderFluid(FluidSpriteType.STILL,forRender,amount,1000,min,max,fluidBuffer,sides);", "OriginalCompleteAfter": "FluidRenderer.renderFluid(FluidSpriteType.STILL,forRender,amount,flow.capacity,min,max,fluidBuffer,sides);", "Before": "FluidRenderer.renderFluid(FluidSpriteType.STILL,forRender,amount,1000,min,max,fluidBuffer,sides)", "After": "FluidRenderer.renderFluid(FluidSpriteType.STILL,forRender,amount,flow.capacity,min,max,fluidBuffer,sides)", "Project": "BuildCraft", "Commit": "137b4729aba7757f58a309123e966ba60122d736", "CompilationUnit": "buildcraft.transport.client.render.PipeFlowRendererFluids", "LineNos": {"_1": 69, "_2": 69}, "Names": {"_1": "amount", "_2": "amount"}, "TemplateVariableToCodeBefore": {"v6": "forRender", "TCIVar": "amount", "v0": "fluidBuffer", "v1": "sides", "v2": "min", "v3": "max", "v5": "FluidSpriteType.STILL"}, "RelevantImports": ["buildcraft.lib.client.render.fluid.FluidRenderer"], "TemplateVariableToCodeAfter": {"v6": "forRender", "TCIVar": "amount", "v0": "fluidBuffer", "v1": "sides", "v2": "min", "v3": "max", "v5": "FluidSpriteType.STILL"}, "isRelevant": "Uses", "isSafe": false}]