[{"OriginalCompleteBefore": "clusterRange = database.getStorage().getUnderlying().getClusterDataRange(clusterId)", "OriginalCompleteAfter": "nextPosition = database.getStorage().getUnderlying().getClusterById(clusterId).getNextPosition()", "Before": "database.getStorage().getUnderlying().getClusterDataRange(clusterId)", "After": "database.getStorage().getUnderlying().getClusterById(clusterId).getNextPosition()", "Project": "orientdb", "Commit": "55034fc016a33901a18250178084df295a3e83b7", "CompilationUnit": "com.orientechnologies.orient.server.distributed.impl.task.OClusterRepairInfoTask", "LineNos": {"_1": 71, "_2": 72}, "Names": {"_1": "clusterRange", "_2": "nextPosition"}, "TemplateVariableToCodeBefore": {"v0": "database.getStorage().getUnderlying()"}, "RelevantImports": [], "TemplateVariableToCodeAfter": {"v0": "database.getStorage().getUnderlying()"}, "isRelevant": "AssignedTo", "isSafe": true}, {"OriginalCompleteBefore": "final long[] clusterRange=database.getStorage().getUnderlying().getClusterDataRange(clusterId);", "OriginalCompleteAfter": "final long nextPosition=database.getStorage().getUnderlying().getClusterById(clusterId).getNextPosition();", "Before": "database.getStorage().getUnderlying().getClusterDataRange(clusterId)", "After": "database.getStorage().getUnderlying().getClusterById(clusterId).getNextPosition()", "Project": "orientdb", "Commit": "55034fc016a33901a18250178084df295a3e83b7", "CompilationUnit": "com.orientechnologies.orient.server.distributed.impl.task.OClusterRepairInfoTask", "LineNos": {"_1": 71, "_2": 72}, "Names": {"_1": "clusterRange", "_2": "nextPosition"}, "TemplateVariableToCodeBefore": {"v0": "database.getStorage().getUnderlying()"}, "RelevantImports": [], "TemplateVariableToCodeAfter": {"v0": "database.getStorage().getUnderlying()"}, "isRelevant": "AssignedTo", "isSafe": true}]