{"Mapping-0": {"Match": "keysToPrefetchBuilder.build()", "Replace": "depKeys.toSet()", "Instances": 1, "Relevant Instances": 1, "Commits": ["a6679aead65603162d57ee5d868ab06fed369fab"], "Project": ["bazel"], "Link": "<a href= ../TypeChange302/Mapping-0.html>Link</a>", "isChange": true, "isGood": false, "isVeryGood": false}, "Mapping-1": {"Match": "Iterables.concat(Iterables.skip(context.original().keySet(),main),Iterables.limit(ImmutableList.copyOf(:[v0]),main))", "Replace": "new LinkedHashSet&lt;&gt;(:[v0])", "Instances": 1, "Relevant Instances": 1, "Commits": ["61dc09a33273c8936d671a09ae9a1acc22d4840a"], "Project": ["caffeine"], "Link": "<a href= ../TypeChange302/Mapping-1.html>Link</a>", "isChange": true, "isGood": false, "isVeryGood": false}, "Mapping-2": {"Match": ":[v0].getRelatedIndexes(changedLabels,unchangedLabels,:[v1])", "Replace": ":[v0].getRelatedIndexes(changedEntityTokens,unchangedEntityTokens,:[v1],entityType)", "Instances": 1, "Relevant Instances": 1, "Commits": ["2d7cd7984293c8548da5afe24d608af5ff235697"], "Project": ["neo4j"], "Link": "<a href= ../TypeChange302/Mapping-2.html>Link</a>", "isChange": true, "isGood": false, "isVeryGood": false}, "Mapping-3": {"Match": ":[v0]", "Replace": ":[v0].toSet()", "Instances": 10, "Relevant Instances": 10, "Commits": ["1526b8fb0f9e6ae89e54abbc5243ab9384bc6a8b"], "Project": ["buck"], "Link": "<a href= ../TypeChange302/Mapping-3.html>Link</a>", "isChange": true, "isGood": false, "isVeryGood": false}}