[{"OriginalCompleteBefore": "return delegate.getRealmRoleMappings();", "OriginalCompleteAfter": "return delegate.getRealmRoleMappingsStream();", "Before": "delegate.getRealmRoleMappings()", "After": "delegate.getRealmRoleMappingsStream()", "Project": "keycloak", "Commit": "5d5e56dde3bc841c7d1d0261cfcaf372cdf119bc", "CompilationUnit": "org.keycloak.models.utils.UserModelDelegate", "LineNos": {"_1": 163, "_2": 163}, "Names": {"_1": "getRealmRoleMappings", "_2": "getRealmRoleMappingsStream"}, "TemplateVariableToCodeBefore": {"v0": "delegate"}, "RelevantImports": [], "TemplateVariableToCodeAfter": {"v0": "delegate"}, "isRelevant": "Returns", "isSafe": true}]