[{"OriginalCompleteBefore": "data=request.getWriteChunk().getData().toByteArray();", "OriginalCompleteAfter": "data=request.getWriteChunk().getData().asReadOnlyByteBuffer();", "Before": "data=request.getWriteChunk().getData().toByteArray()", "After": "data=request.getWriteChunk().getData().asReadOnlyByteBuffer()", "Project": "hadoop", "Commit": "942693bddd5fba51b85a5f677e3496a41817cff3", "CompilationUnit": "org.apache.hadoop.ozone.container.keyvalue.KeyValueHandler", "LineNos": {"_1": 655, "_2": 656}, "Names": {"_1": "data", "_2": "data"}, "TemplateVariableToCodeBefore": {"TCIVar": "data", "v1": "request.getWriteChunk().getData()"}, "RelevantImports": [], "TemplateVariableToCodeAfter": {"TCIVar": "data", "v1": "request.getWriteChunk().getData()"}, "isRelevant": "Uses", "isSafe": true}]