[{"OriginalCompleteBefore": "expected = new LinkedList<>()", "OriginalCompleteAfter": "actual = new ArrayList<>()", "Before": "new LinkedList<>()", "After": "new ArrayList<>()", "Project": "neo4j", "Commit": "25fe58b74f7dc85a32d576bc15b3c62a1547059e", "CompilationUnit": "org.neo4j.coreedge.raft.CatchUpTest", "LineNos": {"_1": 116, "_2": 118}, "Names": {"_1": "expected", "_2": "actual"}, "TemplateVariableToCodeBefore": {"v0": ""}, "RelevantImports": ["java.util.ArrayList"], "TemplateVariableToCodeAfter": {"v0": ""}, "isRelevant": "AssignedTo", "isSafe": true}, {"OriginalCompleteBefore": "LinkedList<Integer> expected=new LinkedList<>();", "OriginalCompleteAfter": "List<Integer> actual=new ArrayList<>();", "Before": "new LinkedList<>()", "After": "new ArrayList<>()", "Project": "neo4j", "Commit": "25fe58b74f7dc85a32d576bc15b3c62a1547059e", "CompilationUnit": "org.neo4j.coreedge.raft.CatchUpTest", "LineNos": {"_1": 116, "_2": 118}, "Names": {"_1": "expected", "_2": "actual"}, "TemplateVariableToCodeBefore": {"v0": ""}, "RelevantImports": ["java.util.ArrayList"], "TemplateVariableToCodeAfter": {"v0": ""}, "isRelevant": "AssignedTo", "isSafe": true}, {"OriginalCompleteBefore": "newBuckets = new LinkedList<>()", "OriginalCompleteAfter": "newBuckets = new ArrayList<>()", "Before": "new LinkedList<>()", "After": "new ArrayList<>()", "Project": "elasticsearch", "Commit": "85a603ee6192055332e7b002b2a170a38bb48774", "CompilationUnit": "org.elasticsearch.search.aggregations.pipeline.BucketSortPipelineAggregator", "LineNos": {"_1": 111, "_2": 109}, "Names": {"_1": "newBuckets", "_2": "newBuckets"}, "TemplateVariableToCodeBefore": {"v0": ""}, "RelevantImports": ["java.util.ArrayList"], "TemplateVariableToCodeAfter": {"v0": ""}, "isRelevant": "AssignedTo", "isSafe": true}, {"OriginalCompleteBefore": "result = new LinkedList<>()", "OriginalCompleteAfter": "result = new ArrayList<>()", "Before": "new LinkedList<>()", "After": "new ArrayList<>()", "Project": "alluxio", "Commit": "1e45a107be06ebd247edd3f3cfe16e8ff748b9a1", "CompilationUnit": "alluxio.underfs.ObjectUnderFileSystem.DeleteBuffer", "LineNos": {"_1": 324, "_2": 323}, "Names": {"_1": "result", "_2": "result"}, "TemplateVariableToCodeBefore": {"v0": ""}, "RelevantImports": ["java.util.ArrayList"], "TemplateVariableToCodeAfter": {"v0": ""}, "isRelevant": "AssignedTo", "isSafe": true}, {"OriginalCompleteBefore": "elements = new LinkedList<>()", "OriginalCompleteAfter": "elements = new ArrayList<>()", "Before": "new LinkedList<>()", "After": "new ArrayList<>()", "Project": "spring-framework", "Commit": "9c08a482d1e321791e84b3ffe5cc71b3b75f74ef", "CompilationUnit": "org.springframework.orm.jpa.support.PersistenceAnnotationBeanPostProcessor", "LineNos": {"_1": 408, "_2": 410}, "Names": {"_1": "elements", "_2": "elements"}, "TemplateVariableToCodeBefore": {"v0": ""}, "RelevantImports": ["java.util.ArrayList"], "TemplateVariableToCodeAfter": {"v0": ""}, "isRelevant": "AssignedTo", "isSafe": true}, {"OriginalCompleteBefore": "allListeners = new LinkedList<>()", "OriginalCompleteAfter": "allListeners = new ArrayList<>()", "Before": "new LinkedList<>()", "After": "new ArrayList<>()", "Project": "spring-framework", "Commit": "9c08a482d1e321791e84b3ffe5cc71b3b75f74ef", "CompilationUnit": "org.springframework.context.event.AbstractApplicationEventMulticaster", "LineNos": {"_1": 216, "_2": 217}, "Names": {"_1": "allListeners", "_2": "allListeners"}, "TemplateVariableToCodeBefore": {"v0": ""}, "RelevantImports": ["java.util.ArrayList"], "TemplateVariableToCodeAfter": {"v0": ""}, "isRelevant": "AssignedTo", "isSafe": true}, {"OriginalCompleteBefore": "currElements = new LinkedList<>()", "OriginalCompleteAfter": "currElements = new ArrayList<>()", "Before": "new LinkedList<>()", "After": "new ArrayList<>()", "Project": "spring-framework", "Commit": "9c08a482d1e321791e84b3ffe5cc71b3b75f74ef", "CompilationUnit": "org.springframework.context.annotation.CommonAnnotationBeanPostProcessor", "LineNos": {"_1": 357, "_2": 358}, "Names": {"_1": "currElements", "_2": "currElements"}, "TemplateVariableToCodeBefore": {"v0": ""}, "RelevantImports": ["java.util.ArrayList"], "TemplateVariableToCodeAfter": {"v0": ""}, "isRelevant": "AssignedTo", "isSafe": true}, {"OriginalCompleteBefore": "elements = new LinkedList<>()", "OriginalCompleteAfter": "elements = new ArrayList<>()", "Before": "new LinkedList<>()", "After": "new ArrayList<>()", "Project": "spring-framework", "Commit": "9c08a482d1e321791e84b3ffe5cc71b3b75f74ef", "CompilationUnit": "org.springframework.context.annotation.CommonAnnotationBeanPostProcessor", "LineNos": {"_1": 353, "_2": 354}, "Names": {"_1": "elements", "_2": "elements"}, "TemplateVariableToCodeBefore": {"v0": ""}, "RelevantImports": ["java.util.ArrayList"], "TemplateVariableToCodeAfter": {"v0": ""}, "isRelevant": "AssignedTo", "isSafe": true}, {"OriginalCompleteBefore": "currDestroyMethods = new LinkedList<>()", "OriginalCompleteAfter": "currDestroyMethods = new ArrayList<>()", "Before": "new LinkedList<>()", "After": "new ArrayList<>()", "Project": "spring-framework", "Commit": "9c08a482d1e321791e84b3ffe5cc71b3b75f74ef", "CompilationUnit": "org.springframework.beans.factory.annotation.InitDestroyAnnotationBeanPostProcessor", "LineNos": {"_1": 205, "_2": 206}, "Names": {"_1": "currDestroyMethods", "_2": "currDestroyMethods"}, "TemplateVariableToCodeBefore": {"v0": ""}, "RelevantImports": ["java.util.ArrayList"], "TemplateVariableToCodeAfter": {"v0": ""}, "isRelevant": "AssignedTo", "isSafe": true}, {"OriginalCompleteBefore": "currInitMethods = new LinkedList<>()", "OriginalCompleteAfter": "currInitMethods = new ArrayList<>()", "Before": "new LinkedList<>()", "After": "new ArrayList<>()", "Project": "spring-framework", "Commit": "9c08a482d1e321791e84b3ffe5cc71b3b75f74ef", "CompilationUnit": "org.springframework.beans.factory.annotation.InitDestroyAnnotationBeanPostProcessor", "LineNos": {"_1": 204, "_2": 205}, "Names": {"_1": "currInitMethods", "_2": "currInitMethods"}, "TemplateVariableToCodeBefore": {"v0": ""}, "RelevantImports": ["java.util.ArrayList"], "TemplateVariableToCodeAfter": {"v0": ""}, "isRelevant": "AssignedTo", "isSafe": true}, {"OriginalCompleteBefore": "destroyMethods = new LinkedList<>()", "OriginalCompleteAfter": "destroyMethods = new ArrayList<>()", "Before": "new LinkedList<>()", "After": "new ArrayList<>()", "Project": "spring-framework", "Commit": "9c08a482d1e321791e84b3ffe5cc71b3b75f74ef", "CompilationUnit": "org.springframework.beans.factory.annotation.InitDestroyAnnotationBeanPostProcessor", "LineNos": {"_1": 200, "_2": 201}, "Names": {"_1": "destroyMethods", "_2": "destroyMethods"}, "TemplateVariableToCodeBefore": {"v0": ""}, "RelevantImports": ["java.util.ArrayList"], "TemplateVariableToCodeAfter": {"v0": ""}, "isRelevant": "AssignedTo", "isSafe": true}, {"OriginalCompleteBefore": "initMethods = new LinkedList<>()", "OriginalCompleteAfter": "initMethods = new ArrayList<>()", "Before": "new LinkedList<>()", "After": "new ArrayList<>()", "Project": "spring-framework", "Commit": "9c08a482d1e321791e84b3ffe5cc71b3b75f74ef", "CompilationUnit": "org.springframework.beans.factory.annotation.InitDestroyAnnotationBeanPostProcessor", "LineNos": {"_1": 199, "_2": 200}, "Names": {"_1": "initMethods", "_2": "initMethods"}, "TemplateVariableToCodeBefore": {"v0": ""}, "RelevantImports": ["java.util.ArrayList"], "TemplateVariableToCodeAfter": {"v0": ""}, "isRelevant": "AssignedTo", "isSafe": true}, {"OriginalCompleteBefore": "currElements = new LinkedList<>()", "OriginalCompleteAfter": "currElements = new ArrayList<>()", "Before": "new LinkedList<>()", "After": "new ArrayList<>()", "Project": "spring-framework", "Commit": "9c08a482d1e321791e84b3ffe5cc71b3b75f74ef", "CompilationUnit": "org.springframework.beans.factory.annotation.AutowiredAnnotationBeanPostProcessor", "LineNos": {"_1": 437, "_2": 436}, "Names": {"_1": "currElements", "_2": "currElements"}, "TemplateVariableToCodeBefore": {"v0": ""}, "RelevantImports": ["java.util.ArrayList"], "TemplateVariableToCodeAfter": {"v0": ""}, "isRelevant": "AssignedTo", "isSafe": true}, {"OriginalCompleteBefore": "elements = new LinkedList<>()", "OriginalCompleteAfter": "elements = new ArrayList<>()", "Before": "new LinkedList<>()", "After": "new ArrayList<>()", "Project": "spring-framework", "Commit": "9c08a482d1e321791e84b3ffe5cc71b3b75f74ef", "CompilationUnit": "org.springframework.beans.factory.annotation.AutowiredAnnotationBeanPostProcessor", "LineNos": {"_1": 433, "_2": 432}, "Names": {"_1": "elements", "_2": "elements"}, "TemplateVariableToCodeBefore": {"v0": ""}, "RelevantImports": ["java.util.ArrayList"], "TemplateVariableToCodeAfter": {"v0": ""}, "isRelevant": "AssignedTo", "isSafe": true}, {"OriginalCompleteBefore": "out = new LinkedList<>()", "OriginalCompleteAfter": "out = new ArrayList<>()", "Before": "new LinkedList<>()", "After": "new ArrayList<>()", "Project": "neo4j", "Commit": "1f47a285b4795b08485cb36e410fd0d2753c245d", "CompilationUnit": "org.neo4j.collection.RawIteratorTest", "LineNos": {"_1": 44, "_2": 44}, "Names": {"_1": "out", "_2": "out"}, "TemplateVariableToCodeBefore": {"v0": ""}, "RelevantImports": ["java.util.ArrayList"], "TemplateVariableToCodeAfter": {"v0": ""}, "isRelevant": "AssignedTo", "isSafe": true}, {"OriginalCompleteBefore": "iterators = new LinkedList<>()", "OriginalCompleteAfter": "iterators = new ArrayList<>()", "Before": "new LinkedList<>()", "After": "new ArrayList<>()", "Project": "neo4j", "Commit": "1f47a285b4795b08485cb36e410fd0d2753c245d", "CompilationUnit": "org.neo4j.internal.helpers.collection.CombiningIterable", "LineNos": {"_1": 44, "_2": 45}, "Names": {"_1": "iterators", "_2": "iterators"}, "TemplateVariableToCodeBefore": {"v0": ""}, "RelevantImports": ["java.util.ArrayList"], "TemplateVariableToCodeAfter": {"v0": ""}, "isRelevant": "AssignedTo", "isSafe": true}, {"OriginalCompleteBefore": "currElements = new LinkedList<>()", "OriginalCompleteAfter": "currElements = new ArrayList<>()", "Before": "new LinkedList<>()", "After": "new ArrayList<>()", "Project": "spring-framework", "Commit": "cf2e0c7959fad8d8f79ffba9a3e14edd65831940", "CompilationUnit": "org.springframework.orm.jpa.support.PersistenceAnnotationBeanPostProcessor", "LineNos": {"_1": 426, "_2": 425}, "Names": {"_1": "currElements", "_2": "currElements"}, "TemplateVariableToCodeBefore": {"v0": ""}, "RelevantImports": ["java.util.ArrayList"], "TemplateVariableToCodeAfter": {"v0": ""}, "isRelevant": "AssignedTo", "isSafe": true}, {"OriginalCompleteBefore": "vars = new LinkedList<>()", "OriginalCompleteAfter": "vars = new ArrayList<>()", "Before": "new LinkedList<>()", "After": "new ArrayList<>()", "Project": "cas", "Commit": "119261b8bcf97f402b6b7dae2483e5e92c2ad36c", "CompilationUnit": "org.apereo.cas.adaptors.duo.web.flow.config.DuoMultifactorWebflowConfigurer", "LineNos": {"_1": 264, "_2": 278}, "Names": {"_1": "vars", "_2": "vars"}, "TemplateVariableToCodeBefore": {"v0": ""}, "RelevantImports": ["java.util.ArrayList"], "TemplateVariableToCodeAfter": {"v0": ""}, "isRelevant": "AssignedTo", "isSafe": true}, {"OriginalCompleteBefore": "starts = new LinkedList<>()", "OriginalCompleteAfter": "starts = new ArrayList<>()", "Before": "new LinkedList<>()", "After": "new ArrayList<>()", "Project": "cas", "Commit": "119261b8bcf97f402b6b7dae2483e5e92c2ad36c", "CompilationUnit": "org.apereo.cas.adaptors.duo.web.flow.config.DuoMultifactorWebflowConfigurer", "LineNos": {"_1": 258, "_2": 272}, "Names": {"_1": "starts", "_2": "starts"}, "TemplateVariableToCodeBefore": {"v0": ""}, "RelevantImports": ["java.util.ArrayList"], "TemplateVariableToCodeAfter": {"v0": ""}, "isRelevant": "AssignedTo", "isSafe": true}, {"OriginalCompleteBefore": "states = new LinkedList<>()", "OriginalCompleteAfter": "states = new ArrayList<>()", "Before": "new LinkedList<>()", "After": "new ArrayList<>()", "Project": "cas", "Commit": "119261b8bcf97f402b6b7dae2483e5e92c2ad36c", "CompilationUnit": "org.apereo.cas.adaptors.duo.web.flow.config.DuoMultifactorWebflowConfigurer", "LineNos": {"_1": 101, "_2": 103}, "Names": {"_1": "states", "_2": "states"}, "TemplateVariableToCodeBefore": {"v0": ""}, "RelevantImports": ["java.util.ArrayList"], "TemplateVariableToCodeAfter": {"v0": ""}, "isRelevant": "AssignedTo", "isSafe": true}, {"OriginalCompleteBefore": "r.fields=new LinkedList<>();", "OriginalCompleteAfter": "r.fields=new ArrayList<>();", "Before": "new LinkedList<>()", "After": "new ArrayList<>()", "Project": "groovy", "Commit": "8c200eca1f48c1cd991b1278aba8b5f9efdc46d5", "CompilationUnit": "org.codehaus.groovy.ast.ClassNode", "LineNos": {"_1": 145, "_2": 145}, "Names": {"_1": "fields", "_2": "fields"}, "TemplateVariableToCodeBefore": {"v0": ""}, "RelevantImports": ["java.util.ArrayList"], "TemplateVariableToCodeAfter": {"v0": ""}, "isRelevant": "AssignedTo", "isSafe": true}, {"OriginalCompleteBefore": "fields=new LinkedList<>();", "OriginalCompleteAfter": "fields=new ArrayList<>();", "Before": "new LinkedList<>()", "After": "new ArrayList<>()", "Project": "groovy", "Commit": "8c200eca1f48c1cd991b1278aba8b5f9efdc46d5", "CompilationUnit": "org.codehaus.groovy.ast.ClassNode", "LineNos": {"_1": 145, "_2": 145}, "Names": {"_1": "fields", "_2": "fields"}, "TemplateVariableToCodeBefore": {"v0": ""}, "RelevantImports": ["java.util.ArrayList"], "TemplateVariableToCodeAfter": {"v0": ""}, "isRelevant": "AssignedTo", "isSafe": true}, {"OriginalCompleteBefore": "toRemove = new LinkedList<>()", "OriginalCompleteAfter": "toRemove = new ArrayList<>()", "Before": "new LinkedList<>()", "After": "new ArrayList<>()", "Project": "hadoop", "Commit": "6f81cc0beea00843b44424417f09d8ee12cd7bae", "CompilationUnit": "org.apache.hadoop.hdfs.server.blockmanagement.DatanodeAdminManager.Monitor", "LineNos": {"_1": 520, "_2": 521}, "Names": {"_1": "toRemove", "_2": "toRemove"}, "TemplateVariableToCodeBefore": {"v0": ""}, "RelevantImports": ["java.util.ArrayList"], "TemplateVariableToCodeAfter": {"v0": ""}, "isRelevant": "AssignedTo", "isSafe": true}, {"OriginalCompleteBefore": "currElements = new LinkedList<>()", "OriginalCompleteAfter": "currElements = new ArrayList<>()", "Before": "new LinkedList<>()", "After": "new ArrayList<>()", "Project": "spring-framework", "Commit": "874574513c47287d86fb8a3e943a81910b587395", "CompilationUnit": "org.springframework.orm.jpa.support.PersistenceAnnotationBeanPostProcessor", "LineNos": {"_1": 406, "_2": 405}, "Names": {"_1": "currElements", "_2": "currElements"}, "TemplateVariableToCodeBefore": {"v0": ""}, "RelevantImports": ["java.util.ArrayList"], "TemplateVariableToCodeAfter": {"v0": ""}, "isRelevant": "AssignedTo", "isSafe": true}]