[{"OriginalCompleteBefore": "LOG.debug(STR0,channelId);", "OriginalCompleteAfter": "LOG.debug(STR1,mChannelId);", "Before": "LOG.debug(STR0,channelId)", "After": "LOG.debug(STR1,channelId)", "Project": "alluxio", "Commit": "b2e7ff6c9ecfce59876941355927cb8b0b2bedd5", "CompilationUnit": "alluxio.security.authentication.SaslStreamClientDriver", "LineNos": {"_1": 123, "_2": 63}, "Names": {"_1": "channelId", "_2": "mChannelId"}, "TemplateVariableToCodeBefore": {"TCIVar": "channelId", "v0": "LOG"}, "RelevantImports": [], "TemplateVariableToCodeAfter": {"TCIVar": "channelId", "v0": "LOG"}, "isRelevant": "Uses", "isSafe": false}]