[{"OriginalCompleteBefore": "accounts = new HashSet<UUID>()", "OriginalCompleteAfter": "accounts = new LinkedList<UUID>()", "Before": "new HashSet<UUID>()", "After": "new LinkedList<UUID>()", "Project": "killbill", "Commit": "7c12d1d5f75483ce32ea761ed13b397a8443de67", "CompilationUnit": "org.killbill.billing.jaxrs.TestAdmin", "LineNos": {"_1": 104, "_2": 104}, "Names": {"_1": "accounts", "_2": "accounts"}, "TemplateVariableToCodeBefore": {"v0": "UUID"}, "RelevantImports": ["java.util.LinkedList"], "TemplateVariableToCodeAfter": {"v0": "UUID"}, "isRelevant": "AssignedTo", "isSafe": true}]