[{"OriginalCompleteBefore": "injector.setKnownConstantFunctions(fnNames);", "OriginalCompleteAfter": "injector.setKnownConstants(fnNames);", "Before": "injector.setKnownConstantFunctions(fnNames)", "After": "injector.setKnownConstants(fnNames)", "Project": "closure-compiler", "Commit": "0ba05361d83a73d01181adf16f51475c05728183", "CompilationUnit": "com.google.javascript.jscomp.InlineFunctions", "LineNos": {"_1": 138, "_2": 139}, "Names": {"_1": "fnNames", "_2": "fnNames"}, "TemplateVariableToCodeBefore": {"TCIVar": "fnNames", "v0": "injector"}, "RelevantImports": [], "TemplateVariableToCodeAfter": {"TCIVar": "fnNames", "v0": "injector"}, "isRelevant": "Uses", "isSafe": true}]