[{"OriginalCompleteBefore": "encodedString = configuration.getString(key)", "OriginalCompleteAfter": "encodedString = configuration.get(key)", "Before": "configuration.getString(key)", "After": "configuration.get(key)", "Project": "flink", "Commit": "9241af09bdbb69a06b18edd115f2d500ba5c14b9", "CompilationUnit": "org.apache.flink.yarn.cli.YarnConfigUtils", "LineNos": {"_1": 82, "_2": 80}, "Names": {"_1": "encodedString", "_2": "encodedString"}, "TemplateVariableToCodeBefore": {"v0": "configuration", "v1": "key"}, "RelevantImports": [], "TemplateVariableToCodeAfter": {"v0": "configuration", "v1": "key"}, "isRelevant": "AssignedTo", "isSafe": true}, {"OriginalCompleteBefore": "urls = configuration.getString(option)", "OriginalCompleteAfter": "urls = configuration.get(option)", "Before": "configuration.getString(option)", "After": "configuration.get(option)", "Project": "flink", "Commit": "9241af09bdbb69a06b18edd115f2d500ba5c14b9", "CompilationUnit": "org.apache.flink.client.cli.ExecutionConfigurationUtils", "LineNos": {"_1": 81, "_2": 73}, "Names": {"_1": "urls", "_2": "urls"}, "TemplateVariableToCodeBefore": {"v0": "configuration", "v1": "option"}, "RelevantImports": [], "TemplateVariableToCodeAfter": {"v0": "configuration", "v1": "option"}, "isRelevant": "AssignedTo", "isSafe": true}]