[{"OriginalCompleteBefore": "this.offsets=Ints.toArray(accumOffsets);", "OriginalCompleteAfter": "this.offsets=Longs.toArray(accumOffsets);", "Before": "Ints.toArray(accumOffsets)", "After": "Longs.toArray(accumOffsets)", "Project": "nd4j", "Commit": "d6bb050916d340335c9a7f3d4bce289340455f59", "CompilationUnit": "org.nd4j.linalg.indexing.ShapeOffsetResolution", "LineNos": {"_1": 27, "_2": 28}, "Names": {"_1": "offsets", "_2": "offsets"}, "TemplateVariableToCodeBefore": {"v0": "accumOffsets"}, "RelevantImports": ["com.google.common.primitives.Longs"], "TemplateVariableToCodeAfter": {"v0": "accumOffsets"}, "isRelevant": "AssignedTo", "isSafe": true}, {"OriginalCompleteBefore": "this.strides=Ints.toArray(accumStrides);", "OriginalCompleteAfter": "this.strides=Longs.toArray(accumStrides);", "Before": "Ints.toArray(accumStrides)", "After": "Longs.toArray(accumStrides)", "Project": "nd4j", "Commit": "9e99099bac18aa0a6474c66add54ff686a9a1264", "CompilationUnit": "org.nd4j.linalg.indexing.ShapeOffsetResolution", "LineNos": {"_1": 29, "_2": 32}, "Names": {"_1": "strides", "_2": "strides"}, "TemplateVariableToCodeBefore": {"v0": "accumStrides"}, "RelevantImports": ["com.google.common.primitives.Longs"], "TemplateVariableToCodeAfter": {"v0": "accumStrides"}, "isRelevant": "AssignedTo", "isSafe": true}, {"OriginalCompleteBefore": "this.shapes=Ints.toArray(accumShape);", "OriginalCompleteAfter": "this.shapes=Longs.toArray(accumShape);", "Before": "Ints.toArray(accumShape)", "After": "Longs.toArray(accumShape)", "Project": "nd4j", "Commit": "9e99099bac18aa0a6474c66add54ff686a9a1264", "CompilationUnit": "org.nd4j.linalg.indexing.ShapeOffsetResolution", "LineNos": {"_1": 29, "_2": 32}, "Names": {"_1": "shapes", "_2": "shapes"}, "TemplateVariableToCodeBefore": {"v0": "accumShape"}, "RelevantImports": ["com.google.common.primitives.Longs"], "TemplateVariableToCodeAfter": {"v0": "accumShape"}, "isRelevant": "AssignedTo", "isSafe": true}]