[{"OriginalCompleteBefore": "profiles=new LinkedHashMap<>();", "OriginalCompleteAfter": "profiles=new TreeMap<>();", "Before": "profiles=new LinkedHashMap<>()", "After": "profiles=new TreeMap<>()", "Project": "pac4j", "Commit": "75deffee624ec92e53997ce76387129e4c2310bb", "CompilationUnit": "org.pac4j.core.profile.ProfileManagerTests", "LineNos": {"_1": 38, "_2": 40}, "Names": {"_1": "profiles", "_2": "profiles"}, "TemplateVariableToCodeBefore": {"TCIVar": "profiles", "v1": ""}, "RelevantImports": [], "TemplateVariableToCodeAfter": {"TCIVar": "profiles", "v1": ""}, "isRelevant": "Uses", "isSafe": true}]