[{"OriginalCompleteBefore": "return (int)TERABYTE;", "OriginalCompleteAfter": "return TERABYTE;", "Before": "(int)TERABYTE", "After": "TERABYTE", "Project": "geode", "Commit": "3ce3437ddaf9c3614b11f066011ed33664259e9f", "CompilationUnit": "org.apache.geode.management.internal.cli.commands.ExportLogsCommand", "LineNos": {"_1": 280, "_2": 368}, "Names": {"_1": "TERABYTE", "_2": "TERABYTE"}, "TemplateVariableToCodeBefore": {"TCIVar": "TERABYTE"}, "RelevantImports": [], "TemplateVariableToCodeAfter": {"TCIVar": "TERABYTE"}, "isRelevant": "Uses", "isSafe": true}, {"OriginalCompleteBefore": "return (int)GIGABYTE;", "OriginalCompleteAfter": "return GIGABYTE;", "Before": "(int)GIGABYTE", "After": "GIGABYTE", "Project": "geode", "Commit": "3ce3437ddaf9c3614b11f066011ed33664259e9f", "CompilationUnit": "org.apache.geode.management.internal.cli.commands.ExportLogsCommand", "LineNos": {"_1": 279, "_2": 367}, "Names": {"_1": "GIGABYTE", "_2": "GIGABYTE"}, "TemplateVariableToCodeBefore": {"TCIVar": "GIGABYTE"}, "RelevantImports": [], "TemplateVariableToCodeAfter": {"TCIVar": "GIGABYTE"}, "isRelevant": "Uses", "isSafe": true}, {"OriginalCompleteBefore": "return (int)MEGABYTE;", "OriginalCompleteAfter": "return MEGABYTE;", "Before": "(int)MEGABYTE", "After": "MEGABYTE", "Project": "geode", "Commit": "3ce3437ddaf9c3614b11f066011ed33664259e9f", "CompilationUnit": "org.apache.geode.management.internal.cli.commands.ExportLogsCommand", "LineNos": {"_1": 278, "_2": 366}, "Names": {"_1": "MEGABYTE", "_2": "MEGABYTE"}, "TemplateVariableToCodeBefore": {"TCIVar": "MEGABYTE"}, "RelevantImports": [], "TemplateVariableToCodeAfter": {"TCIVar": "MEGABYTE"}, "isRelevant": "Uses", "isSafe": true}]