[{"OriginalCompleteBefore": "this.maxThreadCount=config.getMaxThreadCount();", "OriginalCompleteAfter": "this.tokenClaimInterval=config.getTokenClaimInterval();", "Before": "config.getMaxThreadCount()", "After": "config.getTokenClaimInterval()", "Project": "AxonFramework", "Commit": "54918e8d514dffce419bc0e5fd1b48a181752413", "CompilationUnit": "org.axonframework.eventhandling.TrackingEventProcessor", "LineNos": {"_1": 85, "_2": 89}, "Names": {"_1": "maxThreadCount", "_2": "tokenClaimInterval"}, "TemplateVariableToCodeBefore": {"v0": "config"}, "RelevantImports": [], "TemplateVariableToCodeAfter": {"v0": "config"}, "isRelevant": "AssignedTo", "isSafe": true}]