[{"OriginalCompleteBefore": "return true;", "OriginalCompleteAfter": "return status;", "Before": "true", "After": "status", "Project": "platform_frameworks_base", "Commit": "1f1bae90736c3cb44f6d9b50db17151d664d680a", "CompilationUnit": "com.android.server.backup.keyvalue.KeyValueBackupTask", "LineNos": {"_1": 804, "_2": 819}, "Names": {"_1": "sendDataToTransport", "_2": "sendDataToTransport"}, "TemplateVariableToCodeBefore": {"xyz": "true"}, "RelevantImports": [], "TemplateVariableToCodeAfter": {"xyz": "status"}, "isRelevant": "Returns", "isSafe": false}, {"OriginalCompleteBefore": "return true;", "OriginalCompleteAfter": "return status;", "Before": "true", "After": "status", "Project": "processing", "Commit": "369822982b51f9a8c70ff1cbc86a57e3f594eada", "CompilationUnit": "processing.opengl.PGL", "LineNos": {"_1": 2051, "_2": 2060}, "Names": {"_1": "validateFramebuffer", "_2": "validateFramebuffer"}, "TemplateVariableToCodeBefore": {"xyz": "true"}, "RelevantImports": [], "TemplateVariableToCodeAfter": {"xyz": "status"}, "isRelevant": "Returns", "isSafe": false}]