[{"OriginalCompleteBefore": "mAnimatingToNewFullscreenState=animatingToNewFullscreenState;", "OriginalCompleteAfter": "mSchedulePipModeChangedState=schedulePipModeChangedState;", "Before": "mAnimatingToNewFullscreenState=animatingToNewFullscreenState", "After": "mAnimatingToNewFullscreenState=schedulePipModeChangedState", "Project": "platform_frameworks_base", "Commit": "8bca9e47c17c86a3092d5384b14713c5b50dd78c", "CompilationUnit": "com.android.server.wm.BoundsAnimationController.BoundsAnimator", "LineNos": {"_1": 129, "_2": 145}, "Names": {"_1": "mAnimatingToNewFullscreenState", "_2": "mSchedulePipModeChangedState"}, "TemplateVariableToCodeBefore": {"TCIVar": "mAnimatingToNewFullscreenState"}, "RelevantImports": [], "TemplateVariableToCodeAfter": {"TCIVar": "mAnimatingToNewFullscreenState"}, "isRelevant": "Uses", "isSafe": false}]