[{"OriginalCompleteBefore": "return tachyonMaster.getBlockMaster().getCapacityBytes();", "OriginalCompleteAfter": "return tachyonMaster.getBlockMaster().getWorkerCount();", "Before": "tachyonMaster.getBlockMaster().getCapacityBytes()", "After": "tachyonMaster.getBlockMaster().getWorkerCount()", "Project": "alluxio", "Commit": "6f142b454f1ae5e15887aedb1aa59eb9c4448135", "CompilationUnit": "tachyon.master.MasterSource.registerGauges.register", "LineNos": {"_1": 107, "_2": 209}, "Names": {"_1": "getValue", "_2": "getValue"}, "TemplateVariableToCodeBefore": {"v0": "tachyonMaster.getBlockMaster()"}, "RelevantImports": [], "TemplateVariableToCodeAfter": {"v0": "tachyonMaster.getBlockMaster()"}, "isRelevant": "Returns", "isSafe": true}]