[{"OriginalCompleteBefore": "indices = defaultIndicesResolver.resolve(request,metaData,buildAuthorizedIndices(userDashIndices,SearchAction.NAME))", "OriginalCompleteAfter": "indices = resolveIndices(request,buildAuthorizedIndices(userDashIndices,SearchAction.NAME)).getLocal()", "Before": "defaultIndicesResolver.resolve(request,metaData,buildAuthorizedIndices(userDashIndices,SearchAction.NAME))", "After": "resolveIndices(request,buildAuthorizedIndices(userDashIndices,SearchAction.NAME)).getLocal()", "Project": "elasticsearch", "Commit": "a73be456ec596c8f96a8c8071581d21ed619475a", "CompilationUnit": "org.elasticsearch.xpack.security.authz.IndicesAndAliasesResolverTests", "LineNos": {"_1": 281, "_2": 292}, "Names": {"_1": "indices", "_2": "indices"}, "TemplateVariableToCodeBefore": {"xyz": "defaultIndicesResolver.resolve(request,metaData,buildAuthorizedIndices(userDashIndices,SearchAction.NAME))"}, "RelevantImports": [], "TemplateVariableToCodeAfter": {"xyz": "resolveIndices(request,buildAuthorizedIndices(userDashIndices,SearchAction.NAME)).getLocal()"}, "isRelevant": "AssignedTo", "isSafe": false}, {"OriginalCompleteBefore": "indices = defaultIndicesResolver.resolve(request,metaData,buildAuthorizedIndices(userDashIndices,SearchAction.NAME))", "OriginalCompleteAfter": "indices = resolveIndices(request,buildAuthorizedIndices(userDashIndices,SearchAction.NAME)).getLocal()", "Before": "defaultIndicesResolver.resolve(request,metaData,buildAuthorizedIndices(userDashIndices,SearchAction.NAME))", "After": "resolveIndices(request,buildAuthorizedIndices(userDashIndices,SearchAction.NAME)).getLocal()", "Project": "elasticsearch", "Commit": "a73be456ec596c8f96a8c8071581d21ed619475a", "CompilationUnit": "org.elasticsearch.xpack.security.authz.IndicesAndAliasesResolverTests", "LineNos": {"_1": 263, "_2": 273}, "Names": {"_1": "indices", "_2": "indices"}, "TemplateVariableToCodeBefore": {"xyz": "defaultIndicesResolver.resolve(request,metaData,buildAuthorizedIndices(userDashIndices,SearchAction.NAME))"}, "RelevantImports": [], "TemplateVariableToCodeAfter": {"xyz": "resolveIndices(request,buildAuthorizedIndices(userDashIndices,SearchAction.NAME)).getLocal()"}, "isRelevant": "AssignedTo", "isSafe": false}, {"OriginalCompleteBefore": "indices = defaultIndicesResolver.resolve(request,metaData,buildAuthorizedIndices(userDashIndices,SearchAction.NAME))", "OriginalCompleteAfter": "indices = resolveIndices(request,buildAuthorizedIndices(userDashIndices,SearchAction.NAME)).getLocal()", "Before": "defaultIndicesResolver.resolve(request,metaData,buildAuthorizedIndices(userDashIndices,SearchAction.NAME))", "After": "resolveIndices(request,buildAuthorizedIndices(userDashIndices,SearchAction.NAME)).getLocal()", "Project": "elasticsearch", "Commit": "a73be456ec596c8f96a8c8071581d21ed619475a", "CompilationUnit": "org.elasticsearch.xpack.security.authz.IndicesAndAliasesResolverTests", "LineNos": {"_1": 252, "_2": 261}, "Names": {"_1": "indices", "_2": "indices"}, "TemplateVariableToCodeBefore": {"xyz": "defaultIndicesResolver.resolve(request,metaData,buildAuthorizedIndices(userDashIndices,SearchAction.NAME))"}, "RelevantImports": [], "TemplateVariableToCodeAfter": {"xyz": "resolveIndices(request,buildAuthorizedIndices(userDashIndices,SearchAction.NAME)).getLocal()"}, "isRelevant": "AssignedTo", "isSafe": false}, {"OriginalCompleteBefore": "indices = defaultIndicesResolver.resolve(request,metaData,buildAuthorizedIndices(userDashIndices,SearchAction.NAME))", "OriginalCompleteAfter": "indices = resolveIndices(request,buildAuthorizedIndices(userDashIndices,SearchAction.NAME)).getLocal()", "Before": "defaultIndicesResolver.resolve(request,metaData,buildAuthorizedIndices(userDashIndices,SearchAction.NAME))", "After": "resolveIndices(request,buildAuthorizedIndices(userDashIndices,SearchAction.NAME)).getLocal()", "Project": "elasticsearch", "Commit": "a73be456ec596c8f96a8c8071581d21ed619475a", "CompilationUnit": "org.elasticsearch.xpack.security.authz.IndicesAndAliasesResolverTests", "LineNos": {"_1": 241, "_2": 249}, "Names": {"_1": "indices", "_2": "indices"}, "TemplateVariableToCodeBefore": {"xyz": "defaultIndicesResolver.resolve(request,metaData,buildAuthorizedIndices(userDashIndices,SearchAction.NAME))"}, "RelevantImports": [], "TemplateVariableToCodeAfter": {"xyz": "resolveIndices(request,buildAuthorizedIndices(userDashIndices,SearchAction.NAME)).getLocal()"}, "isRelevant": "AssignedTo", "isSafe": false}, {"OriginalCompleteBefore": "indices = defaultIndicesResolver.resolve(request,metaData,buildAuthorizedIndices(userDashIndices,SearchAction.NAME))", "OriginalCompleteAfter": "indices = resolveIndices(request,buildAuthorizedIndices(userDashIndices,SearchAction.NAME)).getLocal()", "Before": "defaultIndicesResolver.resolve(request,metaData,buildAuthorizedIndices(userDashIndices,SearchAction.NAME))", "After": "resolveIndices(request,buildAuthorizedIndices(userDashIndices,SearchAction.NAME)).getLocal()", "Project": "elasticsearch", "Commit": "a73be456ec596c8f96a8c8071581d21ed619475a", "CompilationUnit": "org.elasticsearch.xpack.security.authz.IndicesAndAliasesResolverTests", "LineNos": {"_1": 231, "_2": 238}, "Names": {"_1": "indices", "_2": "indices"}, "TemplateVariableToCodeBefore": {"xyz": "defaultIndicesResolver.resolve(request,metaData,buildAuthorizedIndices(userDashIndices,SearchAction.NAME))"}, "RelevantImports": [], "TemplateVariableToCodeAfter": {"xyz": "resolveIndices(request,buildAuthorizedIndices(userDashIndices,SearchAction.NAME)).getLocal()"}, "isRelevant": "AssignedTo", "isSafe": false}, {"OriginalCompleteBefore": "indices = defaultIndicesResolver.resolve(request,metaData,buildAuthorizedIndices(userDashIndices,SearchAction.NAME))", "OriginalCompleteAfter": "indices = resolveIndices(request,buildAuthorizedIndices(userDashIndices,SearchAction.NAME)).getLocal()", "Before": "defaultIndicesResolver.resolve(request,metaData,buildAuthorizedIndices(userDashIndices,SearchAction.NAME))", "After": "resolveIndices(request,buildAuthorizedIndices(userDashIndices,SearchAction.NAME)).getLocal()", "Project": "elasticsearch", "Commit": "a73be456ec596c8f96a8c8071581d21ed619475a", "CompilationUnit": "org.elasticsearch.xpack.security.authz.IndicesAndAliasesResolverTests", "LineNos": {"_1": 216, "_2": 222}, "Names": {"_1": "indices", "_2": "indices"}, "TemplateVariableToCodeBefore": {"xyz": "defaultIndicesResolver.resolve(request,metaData,buildAuthorizedIndices(userDashIndices,SearchAction.NAME))"}, "RelevantImports": [], "TemplateVariableToCodeAfter": {"xyz": "resolveIndices(request,buildAuthorizedIndices(userDashIndices,SearchAction.NAME)).getLocal()"}, "isRelevant": "AssignedTo", "isSafe": false}, {"OriginalCompleteBefore": "indices = defaultIndicesResolver.resolve(request,metaData,buildAuthorizedIndices(userDashIndices,SearchAction.NAME))", "OriginalCompleteAfter": "indices = resolveIndices(request,buildAuthorizedIndices(userDashIndices,SearchAction.NAME)).getLocal()", "Before": "defaultIndicesResolver.resolve(request,metaData,buildAuthorizedIndices(userDashIndices,SearchAction.NAME))", "After": "resolveIndices(request,buildAuthorizedIndices(userDashIndices,SearchAction.NAME)).getLocal()", "Project": "elasticsearch", "Commit": "a73be456ec596c8f96a8c8071581d21ed619475a", "CompilationUnit": "org.elasticsearch.xpack.security.authz.IndicesAndAliasesResolverTests", "LineNos": {"_1": 182, "_2": 185}, "Names": {"_1": "indices", "_2": "indices"}, "TemplateVariableToCodeBefore": {"xyz": "defaultIndicesResolver.resolve(request,metaData,buildAuthorizedIndices(userDashIndices,SearchAction.NAME))"}, "RelevantImports": [], "TemplateVariableToCodeAfter": {"xyz": "resolveIndices(request,buildAuthorizedIndices(userDashIndices,SearchAction.NAME)).getLocal()"}, "isRelevant": "AssignedTo", "isSafe": false}]