{"Mapping-0": {"Match": ":[TCIVar].contains(:[v1])", "Replace": ":[TCIVar].containsKey(:[v1])", "Instances": 4, "Relevant Instances": 4, "Commits": ["e13cf75176f259b558e7df4abfcdc11b85b4b732", "3d950f3aa54a896ffc674a2845247c575811ed8b", "99545bf618d12e797d4ce8a7aab2c6ebde29d869"], "Project": ["elasticsearch", "alluxio", "presto"], "Link": "<a href= ../TypeChange61/Mapping-0.html>Link</a>", "isChange": true, "isGood": true, "isVeryGood": true}, "Mapping-1": {"Match": ":[v0] &amp;&amp; :[TCIVar].contains(:[v1])", "Replace": ":[v0] &amp;&amp; :[TCIVar].containsKey(:[v1])", "Instances": 1, "Relevant Instances": 1, "Commits": ["e13cf75176f259b558e7df4abfcdc11b85b4b732"], "Project": ["elasticsearch"], "Link": "<a href= ../TypeChange61/Mapping-1.html>Link</a>", "isChange": true, "isGood": false, "isVeryGood": false}, "Mapping-2": {"Match": "new HashSet&lt;:[v0]&gt;()", "Replace": "new HashMap&lt;:[v0]&gt;()", "Instances": 1, "Relevant Instances": 1, "Commits": ["3d950f3aa54a896ffc674a2845247c575811ed8b"], "Project": ["alluxio"], "Link": "<a href= ../TypeChange61/Mapping-2.html>Link</a>", "isChange": true, "isGood": false, "isVeryGood": false}}