[{"OriginalCompleteBefore": "this.mLabels=new HashMap<String,String>(labels);", "OriginalCompleteAfter": "mLabels=new HashMap<ULocale,String>(labels);", "Before": "new HashMap<String,String>(labels)", "After": "new HashMap<ULocale,String>(labels)", "Project": "platform_frameworks_base", "Commit": "5272e68cde1bf97e9644e18e12a3cb54700c4dba", "CompilationUnit": "android.media.AudioPresentation", "LineNos": {"_1": 52, "_2": 70}, "Names": {"_1": "mLabels", "_2": "mLabels"}, "TemplateVariableToCodeBefore": {"v0": "labels"}, "RelevantImports": ["java.util.HashMap"], "TemplateVariableToCodeAfter": {"v0": "labels"}, "isRelevant": "AssignedTo", "isSafe": true}]