[{"OriginalCompleteBefore": "canonicalizedMissing = new ArrayList<>()", "OriginalCompleteAfter": "canonicalizedMissing = new LinkedHashSet<>()", "Before": "new ArrayList<>()", "After": "new LinkedHashSet<>()", "Project": "bazel", "Commit": "17795caaa2eb6e05b107502a57e929f1b0224344", "CompilationUnit": "com.google.devtools.build.buildjar.javac.plugins.dependency.StrictJavaDepsPlugin", "LineNos": {"_1": 174, "_2": 173}, "Names": {"_1": "canonicalizedMissing", "_2": "canonicalizedMissing"}, "TemplateVariableToCodeBefore": {"v0": ""}, "RelevantImports": ["java.util.LinkedHashSet"], "TemplateVariableToCodeAfter": {"v0": ""}, "isRelevant": "AssignedTo", "isSafe": true}, {"OriginalCompleteBefore": "refs=new ArrayList<>();", "OriginalCompleteAfter": "refs=new LinkedHashSet<>();", "Before": "new ArrayList<>()", "After": "new LinkedHashSet<>()", "Project": "closure-compiler", "Commit": "934911ef63a4a7a156a50489116fea197e9fe22a", "CompilationUnit": "com.google.javascript.jscomp.GlobalNamespace.Name", "LineNos": {"_1": 1069, "_2": 1073}, "Names": {"_1": "refs", "_2": "refs"}, "TemplateVariableToCodeBefore": {"v0": ""}, "RelevantImports": ["java.util.LinkedHashSet"], "TemplateVariableToCodeAfter": {"v0": ""}, "isRelevant": "AssignedTo", "isSafe": true}]